piapi.py
piapi-0.1.5.dist-info/LICENSE
piapi-0.1.5.dist-info/METADATA
piapi-0.1.5.dist-info/WHEEL
piapi-0.1.5.dist-info/top_level.txt
piapi-0.1.5.dist-info/RECORD
