Metadata-Version: 2.1
Name: piapi
Version: 0.1.5
Summary: Cisco Prime Infrastructure REST API for python
Home-page: https://github.com/HSRNetwork/piapi
Author: maximumG
Author-email: mgerges@stubbynet.com
License: Apache
Download-URL: https://github.com/HSRNetwork/piapi/archive/0.1.5.tar.gz
Keywords: Cisco,Prime,API,REST,request
Platform: any
Classifier: Environment :: Web Environment
Classifier: Intended Audience :: Developers
Classifier: License :: OSI Approved :: Apache Software License
Classifier: Programming Language :: Python :: 3
Classifier: Topic :: Internet :: WWW/HTTP :: Dynamic Content
Classifier: Topic :: Software Development :: Libraries :: Python Modules
Requires-Dist: requests
Requires-Dist: six
